ds/__init__.py
ds/all.py
ds/avl.py
ds/binarytree.py
ds/bst.py
ds/dll.py
ds/graph.py
ds/inset.py
ds/redblacktree.py
ds/segmenttree.py
ds/sll.py
ds/treeset.py
ds/trie.py
dspack-0.0.2.dist-info/LICENSE.txt
dspack-0.0.2.dist-info/METADATA
dspack-0.0.2.dist-info/WHEEL
dspack-0.0.2.dist-info/top_level.txt
dspack-0.0.2.dist-info/RECORD
