Metadata-Version: 2.1
Name: dspack
Version: 0.0.2
Summary: Python Package of datastructures inbuilt
Home-page: https://code.swecha.org/SANJAY/python_package_contirbution
Author: Sanjay
Author-email: vsanjaychowdary1999@gmail.com
License: UNKNOWN
Platform: UNKNOWN
Classifier: Programming Language :: Python :: 3
Classifier: License :: OSI Approved :: MIT License
Classifier: Operating System :: OS Independent
Requires-Python: >=3.6
